mcp_deepthinking/__init__.py
mcp_deepthinking/__main__.py
mcp_deepthinking/server.py
mcp_deepthinking-0.1.12.dist-info/METADATA
mcp_deepthinking-0.1.12.dist-info/WHEEL
mcp_deepthinking-0.1.12.dist-info/entry_points.txt
mcp_deepthinking-0.1.12.dist-info/RECORD
