Metadata-Version: 2.4
Name: mcp-deepthinking
Version: 0.1.12
Summary: MCP server providing a 'deepthinking' tool powered by Groq LLMs for complex reasoning.
Author: jeongsk
License-Expression: MIT AND (Apache-2.0 OR BSD-2-Clause)
Keywords: deepthinking,llm,mcp
Classifier: Intended Audience :: Developers
Classifier: License :: OSI Approved :: MIT License
Classifier: Programming Language :: Python :: 3
Classifier: Programming Language :: Python :: 3.11
Requires-Python: >=3.11
Requires-Dist: fastmcp>=0.4.1
Requires-Dist: langchain-anthropic>=0.3.10
Requires-Dist: langchain-groq>=0.3.2
Requires-Dist: langchain-mcp-adapters>=0.0.7
Requires-Dist: langgraph>=0.3.25
Requires-Dist: logging>=0.4.9.6
Requires-Dist: mcp[cli]>=1.6.0
Requires-Dist: python-dotenv>=1.1.0
